MANIFEST.in
README.rst
setup.py
docs/HISTORY.txt
docs/LICENSE.GPL
docs/LICENSE.txt
ftw/__init__.py
ftw.uploadutility.egg-info/PKG-INFO
ftw.uploadutility.egg-info/SOURCES.txt
ftw.uploadutility.egg-info/dependency_links.txt
ftw.uploadutility.egg-info/entry_points.txt
ftw.uploadutility.egg-info/namespace_packages.txt
ftw.uploadutility.egg-info/not-zip-safe
ftw.uploadutility.egg-info/requires.txt
ftw.uploadutility.egg-info/top_level.txt
ftw/uploadutility/__init__.py
ftw/uploadutility/configure.zcml
ftw/uploadutility/factories.py
ftw/uploadutility/upgrades/__init__.py